{"meta":{"status":200},"data":[{"slug":"準備","is_common":true,"tags":["wanikani23","wanikani25"],"jlpt":["jlpt-n3"],"japanese":[{"word":"準備","reading":"じゅんび"}],"senses":[{"english_definitions":["preparation","arrangements","getting ready","provision","setup","reserving"],"parts_of_speech":["Noun","Suru verb","Transitive verb"],"links":[],"tags":[],"restrictions":[],"see_also":[],"antonyms":[],"source":[],"info":[]}],"attribution":{"jmdict":true,"jmnedict":false,"dbpedia":false}},{"slug":"備える","is_common":true,"tags":["wanikani23"],"jlpt":["jlpt-n3","jlpt-n2"],"japanese":[{"word":"備える","reading":"そなえる"},{"word":"具える","reading":"そなえる"}],"senses":[{"english_definitions":["to furnish with","to equip with","to provide","to install"],"parts_of_speech":["Ichidan verb","Transitive verb"],"links":[],"tags":[],"restrictions":[],"see_also":[],"antonyms":[],"source":[],"info":[]},{"english_definitions":["to prepare for","to make preparations for","to make provision for"],"parts_of_speech":["Ichidan verb","Transitive verb"],"links":[],"tags":[],"restrictions":[],"see_also":[],"antonyms":[],"source":[],"info":[]},{"english_definitions":["to possess (all that is needed)","to be endowed with","to be equipped with"],"parts_of_speech":["Ichidan verb","Transitive verb"],"links":[],"tags":[],"restrictions":[],"see_also":[],"antonyms":[],"source":[],"info":[]},{"english_definitions":["to be born with","to have since birth"],"parts_of_speech":["Ichidan verb","Transitive verb"],"links":[],"tags":[],"restrictions":[],"see_also":[],"antonyms":[],"source":[],"info":[]}],"attribution":{"jmdict":true,"jmnedict":false,"dbpedia":false}},{"slug":"設備","is_common":true,"tags":[],"jlpt":["jlpt-n3"],"japanese":[{"word":"設備","reading":"せつび"}],"senses":[{"english_definitions":["equipment","facilities","installation","accommodations","conveniences","arrangements"],"parts_of_speech":["Noun","Suru verb","Transitive verb"],"links":[],"tags":[],"restrictions":[],"see_also":[],"antonyms":[],"source":[],"info":[]}],"attribution":{"jmdict":true,"jmnedict":false,"dbpedia":false}},{"slug":"予備","is_common":true,"tags":[],"jlpt":["jlpt-n2"],"japanese":[{"word":"予備","reading":"よび"},{"word":"預備","reading":"よび"}],"senses":[{"english_definitions":["reserve","spare"],"parts_of_speech":["Noun","Noun which may take the genitive case particle 'no'"],"links":[],"tags":[],"restrictions":[],"see_also":[],"antonyms":[],"source":[],"info":[]},{"english_definitions":["preparation","preliminaries"],"parts_of_speech":["Noun","Noun which may take the genitive case particle 'no'"],"links":[],"tags":[],"restrictions":[],"see_also":[],"antonyms":[],"source":[],"info":[]}],"attribution":{"jmdict":true,"jmnedict":false,"dbpedia":false}},{"slug":"整備","is_common":true,"tags":[],"jlpt":["jlpt-n2"],"japanese":[{"word":"整備","reading":"せいび"}],"senses":[{"english_definitions":["maintenance","servicing"],"parts_of_speech":["Noun","Suru verb"],"links":[],"tags":[],"restrictions":[],"see_also":[],"antonyms":[],"source":[],"info":[]},{"english_definitions":["putting in place","establishment","development","preparation","provision","outfitting"],"parts_of_speech":["Noun","Suru verb"],"links":[],"tags":[],"restrictions":[],"see_also":[],"antonyms":[],"source":[],"info":[]}],"attribution":{"jmdict":true,"jmnedict":false,"dbpedia":false}},{"slug":"警備","is_common":true,"tags":[],"jlpt":["jlpt-n2"],"japanese":[{"word":"警備","reading":"けいび"}],"senses":[{"english_definitions":["defense","defence","guard","policing","security"],"parts_of_speech":["Noun","Suru verb","Transitive verb"],"links":[],"tags":[],"restrictions":[],"see_also":[],"antonyms":[],"source":[],"info":[]}],"attribution":{"jmdict":true,"jmnedict":false,"dbpedia":false}},{"slug":"装備","is_common":true,"tags":[],"jlpt":["jlpt-n1"],"japanese":[{"word":"装備","reading":"そうび"}],"senses":[{"english_definitions":["equipment"],"parts_of_speech":["Noun","Suru verb","Transitive verb"],"links":[],"tags":[],"restrictions":[],"see_also":[],"antonyms":[],"source":[],"info":[]}],"attribution":{"jmdict":true,"jmnedict":false,"dbpedia":false}},{"slug":"備わる","is_common":true,"tags":[],"jlpt":["jlpt-n1"],"japanese":[{"word":"備わる","reading":"そなわる"},{"word":"具わる","reading":"そなわる"}],"senses":[{"english_definitions":["to be furnished with","to be provided with","to be equipped with"],"parts_of_speech":["Godan verb with ru ending","Intransitive verb"],"links":[],"tags":[],"restrictions":[],"see_also":[],"antonyms":[],"source":[],"info":[]},{"english_definitions":["to be possessed of","to be endowed with","to be gifted with"],"parts_of_speech":["Godan verb with ru ending","Intransitive verb"],"links":[],"tags":[],"restrictions":[],"see_also":[],"antonyms":[],"source":[],"info":[]},{"english_definitions":["to be among","to be one of"],"parts_of_speech":["Godan verb with ru ending","Intransitive verb"],"links":[],"tags":[],"restrictions":[],"see_also":[],"antonyms":[],"source":[],"info":[]}],"attribution":{"jmdict":true,"jmnedict":false,"dbpedia":false}},{"slug":"守備","is_common":true,"tags":[],"jlpt":["jlpt-n1"],"japanese":[{"word":"守備","reading":"しゅび"}],"senses":[{"english_definitions":["defense","defence"],"parts_of_speech":["Noun","Suru verb","Transitive verb","Noun which may take the genitive case particle 'no'"],"links":[],"tags":[],"restrictions":[],"see_also":[],"antonyms":["攻撃"],"source":[],"info":[]}],"attribution":{"jmdict":true,"jmnedict":false,"dbpedia":false}},{"slug":"軍備","is_common":true,"tags":[],"jlpt":["jlpt-n1"],"japanese":[{"word":"軍備","reading":"ぐんび"}],"senses":[{"english_definitions":["armaments","military preparations"],"parts_of_speech":["Noun"],"links":[],"tags":[],"restrictions":[],"see_also":[],"antonyms":[],"source":[],"info":[]}],"attribution":{"jmdict":true,"jmnedict":false,"dbpedia":false}},{"slug":"備え付ける","is_common":true,"tags":[],"jlpt":["jlpt-n1"],"japanese":[{"word":"備え付ける","reading":"そなえつける"},{"word":"備えつける","reading":"そなえつける"}],"senses":[{"english_definitions":["to provide","to furnish","to equip","to install"],"parts_of_speech":["Ichidan verb","Transitive verb"],"links":[],"tags":[],"restrictions":[],"see_also":[],"antonyms":[],"source":[],"info":[]}],"attribution":{"jmdict":true,"jmnedict":false,"dbpedia":false}},{"slug":"備え","is_common":true,"tags":[],"jlpt":[],"japanese":[{"word":"備え","reading":"そなえ"}],"senses":[{"english_definitions":["preparation","provision","guarding"],"parts_of_speech":["Noun"],"links":[],"tags":[],"restrictions":[],"see_also":[],"antonyms":[],"source":[],"info":[]}],"attribution":{"jmdict":true,"jmnedict":false,"dbpedia":false}},{"slug":"不備","is_common":true,"tags":[],"jlpt":[],"japanese":[{"word":"不備","reading":"ふび"}],"senses":[{"english_definitions":["defect","deficiency","imperfection","inadequacy","lack"],"parts_of_speech":["Noun","Na-adjective (keiyodoshi)","Noun which may take the genitive case particle 'no'"],"links":[],"tags":[],"restrictions":[],"see_also":[],"antonyms":[],"source":[],"info":[]},{"english_definitions":["Yours in haste"],"parts_of_speech":["Expressions (phrases, clauses, etc.)"],"links":[],"tags":[],"restrictions":[],"see_also":[],"antonyms":[],"source":[],"info":["valediction of a letter"]}],"attribution":{"jmdict":true,"jmnedict":false,"dbpedia":false}},{"slug":"兼ね備える","is_common":true,"tags":[],"jlpt":[],"japanese":[{"word":"兼ね備える","reading":"かねそなえる"}],"senses":[{"english_definitions":["to have both","to possess both","to combine with"],"parts_of_speech":["Ichidan verb","Transitive verb"],"links":[],"tags":[],"restrictions":[],"see_also":[],"antonyms":[],"source":[],"info":[]}],"attribution":{"jmdict":true,"jmnedict":false,"dbpedia":false}},{"slug":"備品","is_common":false,"tags":[],"jlpt":[],"japanese":[{"word":"備品","reading":"びひん"}],"senses":[{"english_definitions":["fixtures","furnishings","equipment"],"parts_of_speech":["Noun"],"links":[],"tags":[],"restrictions":[],"see_also":[],"antonyms":[],"source":[],"info":[]}],"attribution":{"jmdict":true,"jmnedict":false,"dbpedia":false}},{"slug":"予備知識","is_common":false,"tags":[],"jlpt":[],"japanese":[{"word":"予備知識","reading":"よびちしき"}],"senses":[{"english_definitions":["background knowledge","prerequisite knowledge"],"parts_of_speech":["Noun"],"links":[],"tags":[],"restrictions":[],"see_also":[],"antonyms":[],"source":[],"info":[]}],"attribution":{"jmdict":true,"jmnedict":false,"dbpedia":false}},{"slug":"警備員","is_common":false,"tags":[],"jlpt":[],"japanese":[{"word":"警備員","reading":"けいびいん"}],"senses":[{"english_definitions":["guard","security (officer)","guardsman"],"parts_of_speech":["Noun"],"links":[],"tags":[],"restrictions":[],"see_also":[],"antonyms":[],"source":[],"info":[]},{"english_definitions":["Security guard"],"parts_of_speech":["Wikipedia definition"],"links":[{"text":"Read “Security guard” on English Wikipedia","url":"http://en.wikipedia.org/wiki/Security_guard?oldid=495084598"},{"text":"Read “警備員” on Japanese Wikipedia","url":"http://ja.wikipedia.org/wiki/警備員?oldid=42492974"}],"tags":[],"restrictions":[],"see_also":[],"antonyms":[],"source":[],"info":[],"sentences":[]}],"attribution":{"jmdict":true,"jmnedict":false,"dbpedia":"http://dbpedia.org/resource/Security_guard"}},{"slug":"予備選挙","is_common":false,"tags":[],"jlpt":[],"japanese":[{"word":"予備選挙","reading":"よびせんきょ"}],"senses":[{"english_definitions":["preliminary election","primary (election)"],"parts_of_speech":["Noun"],"links":[],"tags":[],"restrictions":[],"see_also":[],"antonyms":[],"source":[],"info":[]},{"english_definitions":["Primary election"],"parts_of_speech":["Wikipedia definition"],"links":[{"text":"Read “Primary election” on English Wikipedia","url":"http://en.wikipedia.org/wiki/Primary_election?oldid=494122488"},{"text":"Read “予備選挙” on Japanese Wikipedia","url":"http://ja.wikipedia.org/wiki/予備選挙?oldid=39595917"}],"tags":[],"restrictions":[],"see_also":[],"antonyms":[],"source":[],"info":[],"sentences":[]}],"attribution":{"jmdict":true,"jmnedict":false,"dbpedia":"http://dbpedia.org/resource/Primary_election"}},{"slug":"設備投資","is_common":false,"tags":[],"jlpt":[],"japanese":[{"word":"設備投資","reading":"せつびとうし"}],"senses":[{"english_definitions":["capital investment","capital expenditure","investment in plant and equipment"],"parts_of_speech":["Noun"],"links":[],"tags":[],"restrictions":[],"see_also":[],"antonyms":[],"source":[],"info":[]}],"attribution":{"jmdict":true,"jmnedict":false,"dbpedia":false}},{"slug":"防音設備","is_common":false,"tags":[],"jlpt":[],"japanese":[{"word":"防音設備","reading":"ぼうおんせつび"}],"senses":[{"english_definitions":["soundproofing"],"parts_of_speech":["Noun"],"links":[],"tags":[],"restrictions":[],"see_also":[],"antonyms":[],"source":[],"info":[]}],"attribution":{"jmdict":true,"jmnedict":false,"dbpedia":false}}]}