{"meta":{"status":200},"data":[{"slug":"公共","is_common":true,"tags":["wanikani11"],"jlpt":["jlpt-n2"],"japanese":[{"word":"公共","reading":"こうきょう"}],"senses":[{"english_definitions":["public (facilities, service, etc.)","communal"],"parts_of_speech":["Noun which may take the genitive case particle 'no'","Noun"],"links":[],"tags":[],"restrictions":[],"see_also":[],"antonyms":[],"source":[],"info":[]},{"english_definitions":["Public"],"parts_of_speech":["Wikipedia definition"],"links":[{"text":"Read “Public” on English Wikipedia","url":"http://en.wikipedia.org/wiki/Public?oldid=484228261"},{"text":"Read “公共” on Japanese Wikipedia","url":"http://ja.wikipedia.org/wiki/公共?oldid=42643270"}],"tags":[],"restrictions":[],"see_also":[],"antonyms":[],"source":[],"info":[],"sentences":[]}],"attribution":{"jmdict":true,"jmnedict":false,"dbpedia":"http://dbpedia.org/resource/Public"}},{"slug":"共鳴","is_common":true,"tags":[],"jlpt":["jlpt-n1"],"japanese":[{"word":"共鳴","reading":"きょうめい"}],"senses":[{"english_definitions":["resonance"],"parts_of_speech":["Noun","Suru verb","Intransitive verb"],"links":[],"tags":["Physics","Chemistry"],"restrictions":[],"see_also":[],"antonyms":[],"source":[],"info":[]},{"english_definitions":["sympathy (with a view, idea, etc.)"],"parts_of_speech":["Noun","Suru verb","Intransitive verb"],"links":[],"tags":[],"restrictions":[],"see_also":[],"antonyms":[],"source":[],"info":[]},{"english_definitions":["Resonance"],"parts_of_speech":["Wikipedia definition"],"links":[{"text":"Read “Resonance” on English Wikipedia","url":"http://en.wikipedia.org/wiki/Resonance?oldid=494911300"},{"text":"Read “共鳴” on Japanese Wikipedia","url":"http://ja.wikipedia.org/wiki/共鳴?oldid=42621345"}],"tags":[],"restrictions":[],"see_also":[],"antonyms":[],"source":[],"info":[],"sentences":[]}],"attribution":{"jmdict":true,"jmnedict":false,"dbpedia":"http://dbpedia.org/resource/Resonance"}},{"slug":"共感","is_common":true,"tags":[],"jlpt":["jlpt-n1"],"japanese":[{"word":"共感","reading":"きょうかん"}],"senses":[{"english_definitions":["sympathy","empathy","response"],"parts_of_speech":["Noun","Suru verb","Intransitive verb","Noun which may take the genitive case particle 'no'"],"links":[],"tags":[],"restrictions":[],"see_also":[],"antonyms":[],"source":[],"info":[]},{"english_definitions":["Empathy"],"parts_of_speech":["Wikipedia definition"],"links":[{"text":"Read “Empathy” on English Wikipedia","url":"http://en.wikipedia.org/wiki/Empathy?oldid=494456161"},{"text":"Read “共感” on Japanese Wikipedia","url":"http://ja.wikipedia.org/wiki/共感?oldid=42536067"}],"tags":[],"restrictions":[],"see_also":[],"antonyms":[],"source":[],"info":[],"sentences":[]}],"attribution":{"jmdict":true,"jmnedict":false,"dbpedia":"http://dbpedia.org/resource/Empathy"}},{"slug":"共同","is_common":true,"tags":["wanikani11"],"jlpt":["jlpt-n3"],"japanese":[{"word":"共同","reading":"きょうどう"},{"word":"協同","reading":"きょうどう"}],"senses":[{"english_definitions":["cooperation","collaboration","association","partnership","(acting in) unison"],"parts_of_speech":["Noun","Suru verb","Intransitive verb","Noun which may take the genitive case particle 'no'"],"links":[],"tags":[],"restrictions":[],"see_also":[],"antonyms":[],"source":[],"info":[]},{"english_definitions":["community","communal use","common possession","sharing"],"parts_of_speech":["Noun","Suru verb","Intransitive verb","Noun which may take the genitive case particle 'no'"],"links":[],"tags":[],"restrictions":["共同"],"see_also":[],"antonyms":[],"source":[],"info":[]},{"english_definitions":["Kyoudou"],"parts_of_speech":["Place"],"links":[],"tags":[],"restrictions":[],"see_also":[],"antonyms":[],"source":[],"info":[]}],"attribution":{"jmdict":true,"jmnedict":true,"dbpedia":false}},{"slug":"協力","is_common":true,"tags":["wanikani14"],"jlpt":["jlpt-n3"],"japanese":[{"word":"協力","reading":"きょうりょく"},{"word":"共力","reading":"きょうりょく"}],"senses":[{"english_definitions":["cooperation","collaboration","help","support"],"parts_of_speech":["Noun","Suru verb","Intransitive verb"],"links":[],"tags":[],"restrictions":[],"see_also":[],"antonyms":[],"source":[],"info":[]}],"attribution":{"jmdict":true,"jmnedict":false,"dbpedia":false}},{"slug":"共に","is_common":true,"tags":[],"jlpt":["jlpt-n3"],"japanese":[{"word":"共に","reading":"ともに"},{"word":"倶に","reading":"ともに"},{"word":"供に","reading":"ともに"}],"senses":[{"english_definitions":["together","jointly"],"parts_of_speech":["Adverb (fukushi)"],"links":[],"tags":["Usually written using kana alone"],"restrictions":[],"see_also":[],"antonyms":[],"source":[],"info":[]},{"english_definitions":["at the same time","with","as ...","including","along with"],"parts_of_speech":["Adverb (fukushi)"],"links":[],"tags":["Usually written using kana alone"],"restrictions":[],"see_also":[],"antonyms":[],"source":[],"info":["often as ...とともに"]},{"english_definitions":["both"],"parts_of_speech":["Adverb (fukushi)"],"links":[],"tags":["Usually written using kana alone"],"restrictions":[],"see_also":[],"antonyms":[],"source":[],"info":[]}],"attribution":{"jmdict":true,"jmnedict":false,"dbpedia":false}},{"slug":"共通","is_common":true,"tags":[],"jlpt":["jlpt-n3"],"japanese":[{"word":"共通","reading":"きょうつう"}],"senses":[{"english_definitions":["common","shared","mutual"],"parts_of_speech":["Noun which may take the genitive case particle 'no'","Na-adjective (keiyodoshi)","Noun"],"links":[],"tags":[],"restrictions":[],"see_also":[],"antonyms":[],"source":[],"info":[]},{"english_definitions":["to be common (to)","to be shared (by)"],"parts_of_speech":["Suru verb","Intransitive verb"],"links":[],"tags":[],"restrictions":[],"see_also":[],"antonyms":[],"source":[],"info":[]},{"english_definitions":["-wide"],"parts_of_speech":["Noun, used as a suffix"],"links":[],"tags":[],"restrictions":[],"see_also":[],"antonyms":[],"source":[],"info":[]}],"attribution":{"jmdict":true,"jmnedict":false,"dbpedia":false}},{"slug":"是非とも","is_common":true,"tags":[],"jlpt":["jlpt-n2","jlpt-n1"],"japanese":[{"word":"是非とも","reading":"ぜひとも"},{"word":"是非共","reading":"ぜひとも"}],"senses":[{"english_definitions":["by all means","at all costs","absolutely"],"parts_of_speech":["Adverb (fukushi)"],"links":[],"tags":[],"restrictions":[],"see_also":[],"antonyms":[],"source":[],"info":[]}],"attribution":{"jmdict":true,"jmnedict":false,"dbpedia":false}},{"slug":"共働き","is_common":true,"tags":[],"jlpt":["jlpt-n1"],"japanese":[{"word":"共働き","reading":"ともばたらき"}],"senses":[{"english_definitions":["(husband and wife) both working","dual income"],"parts_of_speech":["Noun","Suru verb","Intransitive verb","Noun which may take the genitive case particle 'no'"],"links":[],"tags":[],"restrictions":[],"see_also":[],"antonyms":[],"source":[],"info":[]}],"attribution":{"jmdict":true,"jmnedict":false,"dbpedia":false}},{"slug":"共稼ぎ","is_common":true,"tags":[],"jlpt":["jlpt-n1"],"japanese":[{"word":"共稼ぎ","reading":"ともかせぎ"},{"word":"共かせぎ","reading":"ともかせぎ"}],"senses":[{"english_definitions":["(husband and wife) earning a living together"],"parts_of_speech":["Noun","Suru verb","Intransitive verb","Noun which may take the genitive case particle 'no'"],"links":[],"tags":[],"restrictions":[],"see_also":["共働き"],"antonyms":[],"source":[],"info":[]}],"attribution":{"jmdict":true,"jmnedict":false,"dbpedia":false}},{"slug":"共産主義","is_common":true,"tags":[],"jlpt":[],"japanese":[{"word":"共産主義","reading":"きょうさんしゅぎ"}],"senses":[{"english_definitions":["communism","collectivism"],"parts_of_speech":["Noun","Noun which may take the genitive case particle 'no'"],"links":[],"tags":[],"restrictions":[],"see_also":[],"antonyms":[],"source":[],"info":[]},{"english_definitions":["Communism"],"parts_of_speech":["Wikipedia definition"],"links":[{"text":"Read “Communism” on English Wikipedia","url":"http://en.wikipedia.org/wiki/Communism?oldid=495254872"},{"text":"Read “共産主義” on Japanese Wikipedia","url":"http://ja.wikipedia.org/wiki/共産主義?oldid=42191543"}],"tags":[],"restrictions":[],"see_also":[],"antonyms":[],"source":[],"info":[],"sentences":[]}],"attribution":{"jmdict":true,"jmnedict":false,"dbpedia":"http://dbpedia.org/resource/Communism"}},{"slug":"共和党","is_common":true,"tags":[],"jlpt":[],"japanese":[{"word":"共和党","reading":"きょうわとう"}],"senses":[{"english_definitions":["Republican Party"],"parts_of_speech":["Noun"],"links":[],"tags":[],"restrictions":[],"see_also":[],"antonyms":[],"source":[],"info":[]},{"english_definitions":["Republican Party"],"parts_of_speech":["Wikipedia definition"],"links":[{"text":"Read “Republican Party” on English Wikipedia","url":"http://en.wikipedia.org/wiki/Republican_Party?oldid=493868393"},{"text":"Read “共和党” on Japanese Wikipedia","url":"http://ja.wikipedia.org/wiki/共和党?oldid=42708041"}],"tags":[],"restrictions":[],"see_also":[],"antonyms":[],"source":[],"info":[],"sentences":[]}],"attribution":{"jmdict":true,"jmnedict":false,"dbpedia":"http://dbpedia.org/resource/Republican_Party"}},{"slug":"共同体","is_common":true,"tags":[],"jlpt":[],"japanese":[{"word":"共同体","reading":"きょうどうたい"},{"word":"協同体","reading":"きょうどうたい"}],"senses":[{"english_definitions":["cooperative body","cooperative system","collective","community"],"parts_of_speech":["Noun"],"links":[],"tags":[],"restrictions":[],"see_also":[],"antonyms":[],"source":[],"info":[]},{"english_definitions":["Community"],"parts_of_speech":["Wikipedia definition"],"links":[{"text":"Read “Community” on English Wikipedia","url":"http://en.wikipedia.org/wiki/Community?oldid=495253565"},{"text":"Read “共同体” on Japanese Wikipedia","url":"http://ja.wikipedia.org/wiki/共同体?oldid=42433226"}],"tags":[],"restrictions":[],"see_also":[],"antonyms":[],"source":[],"info":[],"sentences":[]}],"attribution":{"jmdict":true,"jmnedict":false,"dbpedia":"http://dbpedia.org/resource/Community"}},{"slug":"公共料金","is_common":true,"tags":[],"jlpt":[],"japanese":[{"word":"公共料金","reading":"こうきょうりょうきん"}],"senses":[{"english_definitions":["public utilities charge"],"parts_of_speech":["Noun"],"links":[],"tags":[],"restrictions":[],"see_also":[],"antonyms":[],"source":[],"info":[]},{"english_definitions":["Cost of living"],"parts_of_speech":["Wikipedia definition"],"links":[{"text":"Read “Cost of living” on English Wikipedia","url":"http://en.wikipedia.org/wiki/Cost_of_living?oldid=495061763"},{"text":"Read “公共料金” on Japanese Wikipedia","url":"http://ja.wikipedia.org/wiki/公共料金?oldid=40582279"}],"tags":[],"restrictions":[],"see_also":[],"antonyms":[],"source":[],"info":[],"sentences":[]}],"attribution":{"jmdict":true,"jmnedict":false,"dbpedia":"http://dbpedia.org/resource/Cost_of_living"}},{"slug":"其れ共","is_common":true,"tags":[],"jlpt":["jlpt-n3","jlpt-n1"],"japanese":[{"word":"其れとも","reading":"それとも"}],"senses":[{"english_definitions":["or","or else"],"parts_of_speech":["Conjunction"],"links":[],"tags":["Usually written using kana alone"],"restrictions":[],"see_also":[],"antonyms":[],"source":[],"info":[]}],"attribution":{"jmdict":true,"jmnedict":false,"dbpedia":false}},{"slug":"共有","is_common":true,"tags":["wanikani11","wanikani13"],"jlpt":[],"japanese":[{"word":"共有","reading":"きょうゆう"}],"senses":[{"english_definitions":["joint ownership","co-ownership","sharing (e.g. a viewpoint)"],"parts_of_speech":["Noun","Suru verb","Transitive verb"],"links":[],"tags":[],"restrictions":[],"see_also":[],"antonyms":[],"source":[],"info":[]},{"english_definitions":["sharing (files, devices on a network, posts on social media, etc.)"],"parts_of_speech":["Noun","Suru verb","Transitive verb"],"links":[],"tags":[],"restrictions":[],"see_also":[],"antonyms":[],"source":[],"info":[]}],"attribution":{"jmdict":true,"jmnedict":false,"dbpedia":false}},{"slug":"共用","is_common":true,"tags":[],"jlpt":[],"japanese":[{"word":"共用","reading":"きょうよう"}],"senses":[{"english_definitions":["common use","communal use","sharing"],"parts_of_speech":["Noun","Suru verb","Transitive verb","Noun which may take the genitive case particle 'no'"],"links":[],"tags":[],"restrictions":[],"see_also":[],"antonyms":[],"source":[],"info":[]}],"attribution":{"jmdict":true,"jmnedict":false,"dbpedia":false}},{"slug":"共立","is_common":true,"tags":[],"jlpt":[],"japanese":[{"word":"共立","reading":"きょうりつ"}],"senses":[{"english_definitions":["joint","common"],"parts_of_speech":["Noun","Suru verb","Transitive verb"],"links":[],"tags":[],"restrictions":[],"see_also":[],"antonyms":[],"source":[],"info":[]}],"attribution":{"jmdict":true,"jmnedict":false,"dbpedia":false}},{"slug":"共済","is_common":true,"tags":[],"jlpt":[],"japanese":[{"word":"共済","reading":"きょうさい"}],"senses":[{"english_definitions":["mutual aid"],"parts_of_speech":["Noun"],"links":[],"tags":[],"restrictions":[],"see_also":[],"antonyms":[],"source":[],"info":[]}],"attribution":{"jmdict":true,"jmnedict":false,"dbpedia":false}},{"slug":"共和国","is_common":true,"tags":[],"jlpt":[],"japanese":[{"word":"共和国","reading":"きょうわこく"}],"senses":[{"english_definitions":["republic","commonwealth"],"parts_of_speech":["Noun"],"links":[],"tags":[],"restrictions":[],"see_also":[],"antonyms":[],"source":[],"info":[]}],"attribution":{"jmdict":true,"jmnedict":false,"dbpedia":false}}]}