{"meta":{"status":200},"data":[{"slug":"左右","is_common":true,"tags":["wanikani2"],"jlpt":["jlpt-n3"],"japanese":[{"word":"左右","reading":"さゆう"},{"word":"左右","reading":"そう"},{"word":"左右","reading":"さう"}],"senses":[{"english_definitions":["left and right","right and left"],"parts_of_speech":["Noun","Suru verb"],"links":[],"tags":[],"restrictions":[],"see_also":[],"antonyms":[],"source":[],"info":[]},{"english_definitions":["(asserting) control","influence","domination"],"parts_of_speech":["Noun","Suru verb"],"links":[],"tags":[],"restrictions":[],"see_also":[],"antonyms":[],"source":[],"info":[]},{"english_definitions":["one's attendants","people accompanying one"],"parts_of_speech":["Noun"],"links":[],"tags":[],"restrictions":[],"see_also":[],"antonyms":[],"source":[],"info":[]},{"english_definitions":["(serving at someone's) side"],"parts_of_speech":["Noun"],"links":[],"tags":[],"restrictions":[],"see_also":[],"antonyms":[],"source":[],"info":[]},{"english_definitions":["equivocation"],"parts_of_speech":["Noun"],"links":[],"tags":[],"restrictions":[],"see_also":[],"antonyms":[],"source":[],"info":[]},{"english_definitions":["Sou"],"parts_of_speech":["Place"],"links":[],"tags":[],"restrictions":[],"see_also":[],"antonyms":[],"source":[],"info":[]},{"english_definitions":["Relative direction"],"parts_of_speech":["Wikipedia definition"],"links":[{"text":"Read “Relative direction” on English Wikipedia","url":"http://en.wikipedia.org/wiki/Relative_direction?oldid=494580891"},{"text":"Read “左右” on Japanese Wikipedia","url":"http://ja.wikipedia.org/wiki/左右?oldid=42590737"}],"tags":[],"restrictions":[],"see_also":[],"antonyms":[],"source":[],"info":[],"sentences":[]}],"attribution":{"jmdict":true,"jmnedict":true,"dbpedia":"http://dbpedia.org/resource/Relative_direction"}},{"slug":"左","is_common":true,"tags":["wanikani2"],"jlpt":["jlpt-n5"],"japanese":[{"word":"左","reading":"ひだり"}],"senses":[{"english_definitions":["left","left hand side"],"parts_of_speech":["Noun","Noun which may take the genitive case particle 'no'"],"links":[],"tags":[],"restrictions":[],"see_also":[],"antonyms":["右 みぎ"],"source":[],"info":[]}],"attribution":{"jmdict":true,"jmnedict":false,"dbpedia":false}},{"slug":"兎角","is_common":true,"tags":[],"jlpt":["jlpt-n1"],"japanese":[{"word":"兎角","reading":"とかく"},{"word":"左右","reading":"とかく"}],"senses":[{"english_definitions":["(doing) various things","(doing) this and that"],"parts_of_speech":["Adverb (fukushi)","Suru verb"],"links":[],"tags":["Usually written using kana alone"],"restrictions":[],"see_also":[],"antonyms":[],"source":[],"info":[]},{"english_definitions":["being apt to","being prone to","tending to"],"parts_of_speech":["Adverb (fukushi)"],"links":[],"tags":["Usually written using kana alone"],"restrictions":[],"see_also":[],"antonyms":[],"source":[],"info":[]},{"english_definitions":["at any rate","anyhow","anyway"],"parts_of_speech":["Adverb (fukushi)"],"links":[],"tags":["Usually written using kana alone"],"restrictions":[],"see_also":[],"antonyms":[],"source":[],"info":[]},{"english_definitions":["all sorts of (negative things)","various"],"parts_of_speech":["Noun which may take the genitive case particle 'no'"],"links":[],"tags":["Usually written using kana alone"],"restrictions":[],"see_also":[],"antonyms":[],"source":[],"info":[]},{"english_definitions":["things that do not exist","rabbit horns"],"parts_of_speech":["Noun"],"links":[],"tags":["Buddhism","Idiomatic expression"],"restrictions":["兎角"],"see_also":["亀毛兎角"],"antonyms":[],"source":[],"info":[]}],"attribution":{"jmdict":true,"jmnedict":false,"dbpedia":false}},{"slug":"左利き","is_common":true,"tags":["wanikani13"],"jlpt":["jlpt-n1"],"japanese":[{"word":"左利き","reading":"ひだりきき"},{"word":"左利","reading":"ひだりきき"}],"senses":[{"english_definitions":["left-handedness","left-handed person","left-hander"],"parts_of_speech":["Noun","Noun which may take the genitive case particle 'no'"],"links":[],"tags":[],"restrictions":[],"see_also":["右利き みぎきき"],"antonyms":[],"source":[],"info":[]},{"english_definitions":["fondness for alcohol","person who is fond of alcohol","drinker"],"parts_of_speech":["Noun","Noun which may take the genitive case particle 'no'"],"links":[],"tags":[],"restrictions":[],"see_also":["左党 さとう"],"antonyms":[],"source":[],"info":[]}],"attribution":{"jmdict":true,"jmnedict":false,"dbpedia":false}},{"slug":"左様なら","is_common":true,"tags":[],"jlpt":["jlpt-n2","jlpt-n1"],"japanese":[{"word":"左様なら","reading":"さようなら"},{"reading":"サヨウナラ"},{"reading":"サヨーナラ"}],"senses":[{"english_definitions":["farewell","adieu","goodbye","so long"],"parts_of_speech":[],"links":[],"tags":["Usually written using kana alone"],"restrictions":[],"see_also":["さよなら"],"antonyms":[],"source":[],"info":[]}],"attribution":{"jmdict":true,"jmnedict":false,"dbpedia":false}},{"slug":"左手","is_common":true,"tags":["wanikani4"],"jlpt":[],"japanese":[{"word":"左手","reading":"ひだりて"}],"senses":[{"english_definitions":["left hand"],"parts_of_speech":["Noun"],"links":[],"tags":[],"restrictions":[],"see_also":[],"antonyms":[],"source":[],"info":[]},{"english_definitions":["left-hand side","left-hand direction","(on) the left"],"parts_of_speech":["Noun","Noun which may take the genitive case particle 'no'"],"links":[],"tags":[],"restrictions":[],"see_also":[],"antonyms":[],"source":[],"info":[]}],"attribution":{"jmdict":true,"jmnedict":false,"dbpedia":false}},{"slug":"左側","is_common":true,"tags":["wanikani17"],"jlpt":[],"japanese":[{"word":"左側","reading":"ひだりがわ"},{"word":"左側","reading":"さそく"}],"senses":[{"english_definitions":["left side","left-hand side"],"parts_of_speech":["Noun","Noun which may take the genitive case particle 'no'"],"links":[],"tags":[],"restrictions":[],"see_also":[],"antonyms":[],"source":[],"info":[]}],"attribution":{"jmdict":true,"jmnedict":false,"dbpedia":false}},{"slug":"左腕","is_common":true,"tags":["wanikani24"],"jlpt":[],"japanese":[{"word":"左腕","reading":"さわん"},{"word":"左腕","reading":"ひだりうで"}],"senses":[{"english_definitions":["left arm"],"parts_of_speech":["Noun"],"links":[],"tags":[],"restrictions":[],"see_also":["右腕"],"antonyms":[],"source":[],"info":[]},{"english_definitions":["left-handed (baseball pitcher)"],"parts_of_speech":["Noun"],"links":[],"tags":[],"restrictions":["さわん"],"see_also":[],"antonyms":[],"source":[],"info":[]}],"attribution":{"jmdict":true,"jmnedict":false,"dbpedia":false}},{"slug":"然程","is_common":false,"tags":[],"jlpt":["jlpt-n1"],"japanese":[{"word":"然程","reading":"さほど"},{"word":"左程","reading":"さほど"}],"senses":[{"english_definitions":["(not) so","(not) particularly","(not) very","(not) that much"],"parts_of_speech":["Adverb (fukushi)"],"links":[],"tags":["Usually written using kana alone"],"restrictions":[],"see_also":[],"antonyms":[],"source":[],"info":["usu. with a negative verb"]}],"attribution":{"jmdict":true,"jmnedict":false,"dbpedia":false}},{"slug":"左派","is_common":true,"tags":[],"jlpt":[],"japanese":[{"word":"左派","reading":"さは"}],"senses":[{"english_definitions":["left wing"],"parts_of_speech":["Noun","Noun which may take the genitive case particle 'no'"],"links":[],"tags":[],"restrictions":[],"see_also":[],"antonyms":[],"source":[],"info":[]}],"attribution":{"jmdict":true,"jmnedict":false,"dbpedia":false}},{"slug":"左足","is_common":true,"tags":[],"jlpt":[],"japanese":[{"word":"左足","reading":"ひだりあし"},{"word":"左脚","reading":"ひだりあし"},{"word":"左足","reading":"さそく"}],"senses":[{"english_definitions":["left foot"],"parts_of_speech":["Noun"],"links":[],"tags":[],"restrictions":[],"see_also":[],"antonyms":[],"source":[],"info":[]},{"english_definitions":["left leg"],"parts_of_speech":["Noun"],"links":[],"tags":[],"restrictions":[],"see_also":[],"antonyms":[],"source":[],"info":[]}],"attribution":{"jmdict":true,"jmnedict":false,"dbpedia":false}},{"slug":"左折","is_common":true,"tags":[],"jlpt":[],"japanese":[{"word":"左折","reading":"させつ"}],"senses":[{"english_definitions":["turning to the left","left turn"],"parts_of_speech":["Noun","Suru verb","Intransitive verb"],"links":[],"tags":[],"restrictions":[],"see_also":["右折"],"antonyms":[],"source":[],"info":[]}],"attribution":{"jmdict":true,"jmnedict":false,"dbpedia":false}},{"slug":"左上","is_common":true,"tags":[],"jlpt":[],"japanese":[{"word":"左上","reading":"ひだりうえ"}],"senses":[{"english_definitions":["upper left"],"parts_of_speech":["Noun","Noun which may take the genitive case particle 'no'"],"links":[],"tags":[],"restrictions":[],"see_also":[],"antonyms":[],"source":[],"info":[]}],"attribution":{"jmdict":true,"jmnedict":false,"dbpedia":false}},{"slug":"右左","is_common":false,"tags":[],"jlpt":[],"japanese":[{"word":"右左","reading":"みぎひだり"}],"senses":[{"english_definitions":["right and left"],"parts_of_speech":["Noun"],"links":[],"tags":[],"restrictions":[],"see_also":[],"antonyms":[],"source":[],"info":[]}],"attribution":{"jmdict":true,"jmnedict":false,"dbpedia":false}},{"slug":"左側通行","is_common":false,"tags":[],"jlpt":[],"japanese":[{"word":"左側通行","reading":"ひだりがわつうこう"}],"senses":[{"english_definitions":["driving on the left side of the road","driving on the left-hand side of the road","left-hand side driving"],"parts_of_speech":["Noun"],"links":[],"tags":[],"restrictions":[],"see_also":["右側通行"],"antonyms":[],"source":[],"info":[]}],"attribution":{"jmdict":true,"jmnedict":false,"dbpedia":false}},{"slug":"左目","is_common":false,"tags":[],"jlpt":[],"japanese":[{"word":"左目","reading":"ひだりめ"}],"senses":[{"english_definitions":["left eye"],"parts_of_speech":["Noun"],"links":[],"tags":[],"restrictions":[],"see_also":[],"antonyms":[],"source":[],"info":[]}],"attribution":{"jmdict":true,"jmnedict":false,"dbpedia":false}},{"slug":"左耳","is_common":false,"tags":[],"jlpt":[],"japanese":[{"word":"左耳","reading":"ひだりみみ"}],"senses":[{"english_definitions":["left ear"],"parts_of_speech":["Noun"],"links":[],"tags":[],"restrictions":[],"see_also":[],"antonyms":[],"source":[],"info":[]}],"attribution":{"jmdict":true,"jmnedict":false,"dbpedia":false}},{"slug":"前後左右","is_common":false,"tags":[],"jlpt":[],"japanese":[{"word":"前後左右","reading":"ぜんごさゆう"}],"senses":[{"english_definitions":["in all directions"],"parts_of_speech":["Noun"],"links":[],"tags":["Yojijukugo (four character compound)"],"restrictions":[],"see_also":[],"antonyms":[],"source":[],"info":[]}],"attribution":{"jmdict":true,"jmnedict":false,"dbpedia":false}},{"slug":"左肩","is_common":false,"tags":[],"jlpt":[],"japanese":[{"word":"左肩","reading":"ひだりかた"}],"senses":[{"english_definitions":["left shoulder"],"parts_of_speech":["Noun"],"links":[],"tags":[],"restrictions":[],"see_also":[],"antonyms":[],"source":[],"info":[]}],"attribution":{"jmdict":true,"jmnedict":false,"dbpedia":false}},{"slug":"証左","is_common":false,"tags":[],"jlpt":[],"japanese":[{"word":"証左","reading":"しょうさ"}],"senses":[{"english_definitions":["evidence","proof"],"parts_of_speech":["Noun"],"links":[],"tags":[],"restrictions":[],"see_also":["証拠"],"antonyms":[],"source":[],"info":[]},{"english_definitions":["witness"],"parts_of_speech":["Noun"],"links":[],"tags":[],"restrictions":[],"see_also":[],"antonyms":[],"source":[],"info":[]}],"attribution":{"jmdict":true,"jmnedict":false,"dbpedia":false}}]}