{"meta":{"status":200},"data":[{"slug":"恥ずかしい","is_common":true,"tags":["wanikani35"],"jlpt":["jlpt-n4"],"japanese":[{"word":"恥ずかしい","reading":"はずかしい"},{"word":"恥かしい","reading":"はずかしい"},{"word":"恥しい","reading":"はずかしい"},{"word":"羞ずかしい","reading":"はずかしい"},{"word":"羞しい","reading":"はずかしい"},{"word":"羞かしい","reading":"はずかしい"}],"senses":[{"english_definitions":["embarrassing","embarrassed","ashamed","humiliated","shy"],"parts_of_speech":["I-adjective (keiyoushi)"],"links":[],"tags":[],"restrictions":[],"see_also":[],"antonyms":[],"source":[],"info":[]},{"english_definitions":["disgraceful","shameful"],"parts_of_speech":["I-adjective (keiyoushi)"],"links":[],"tags":[],"restrictions":[],"see_also":[],"antonyms":[],"source":[],"info":[]}],"attribution":{"jmdict":true,"jmnedict":false,"dbpedia":false}},{"slug":"恥じる","is_common":true,"tags":[],"jlpt":["jlpt-n1"],"japanese":[{"word":"恥じる","reading":"はじる"},{"word":"羞じる","reading":"はじる"},{"word":"耻じる","reading":"はじる"},{"word":"愧じる","reading":"はじる"},{"word":"慙じる","reading":"はじる"}],"senses":[{"english_definitions":["to feel ashamed"],"parts_of_speech":["Ichidan verb"],"links":[],"tags":[],"restrictions":[],"see_also":[],"antonyms":[],"source":[],"info":[]}],"attribution":{"jmdict":true,"jmnedict":false,"dbpedia":false}},{"slug":"恥","is_common":true,"tags":["wanikani35"],"jlpt":["jlpt-n1"],"japanese":[{"word":"恥","reading":"はじ"},{"word":"辱","reading":"はじ"},{"word":"羞","reading":"はじ"},{"word":"耻","reading":"はじ"},{"word":"恥じ","reading":"はじ"},{"word":"辱","reading":"じょく"}],"senses":[{"english_definitions":["shame","embarrassment","disgrace"],"parts_of_speech":["Noun"],"links":[],"tags":[],"restrictions":[],"see_also":[],"antonyms":[],"source":[],"info":[]}],"attribution":{"jmdict":true,"jmnedict":false,"dbpedia":false}},{"slug":"恥知らず","is_common":true,"tags":["wanikani37"],"jlpt":[],"japanese":[{"word":"恥知らず","reading":"はじしらず"}],"senses":[{"english_definitions":["shameless","shameless person"],"parts_of_speech":["Na-adjective (keiyodoshi)","Noun"],"links":[],"tags":[],"restrictions":[],"see_also":[],"antonyms":[],"source":[],"info":[]}],"attribution":{"jmdict":true,"jmnedict":false,"dbpedia":false}},{"slug":"恥じらい","is_common":false,"tags":[],"jlpt":[],"japanese":[{"word":"恥じらい","reading":"はじらい"},{"word":"恥らい","reading":"はじらい"},{"word":"羞じらい","reading":"はじらい"},{"word":"羞い","reading":"はじらい"},{"word":"羞らい","reading":"はじらい"}],"senses":[{"english_definitions":["shyness"],"parts_of_speech":["Noun"],"links":[],"tags":[],"restrictions":[],"see_also":[],"antonyms":[],"source":[],"info":[]}],"attribution":{"jmdict":true,"jmnedict":false,"dbpedia":false}},{"slug":"羞恥心","is_common":false,"tags":[],"jlpt":[],"japanese":[{"word":"羞恥心","reading":"しゅうちしん"}],"senses":[{"english_definitions":["shyness","shame"],"parts_of_speech":["Noun"],"links":[],"tags":[],"restrictions":[],"see_also":[],"antonyms":[],"source":[],"info":[]},{"english_definitions":["Shame"],"parts_of_speech":["Wikipedia definition"],"links":[{"text":"Read “Shame” on English Wikipedia","url":"http://en.wikipedia.org/wiki/Shame?oldid=488861528"},{"text":"Read “羞恥心” on Japanese Wikipedia","url":"http://ja.wikipedia.org/wiki/羞恥心?oldid=42504097"}],"tags":[],"restrictions":[],"see_also":[],"antonyms":[],"source":[],"info":[],"sentences":[]}],"attribution":{"jmdict":true,"jmnedict":false,"dbpedia":"http://dbpedia.org/resource/Shame"}},{"slug":"恥じらう","is_common":false,"tags":[],"jlpt":["jlpt-n1"],"japanese":[{"word":"恥じらう","reading":"はじらう"},{"word":"羞じらう","reading":"はじらう"},{"word":"恥らう","reading":"はじらう"}],"senses":[{"english_definitions":["to feel shy","to be bashful","to blush"],"parts_of_speech":["Godan verb with u ending","Intransitive verb"],"links":[],"tags":[],"restrictions":[],"see_also":[],"antonyms":[],"source":[],"info":[]}],"attribution":{"jmdict":true,"jmnedict":false,"dbpedia":false}},{"slug":"恥ずかしがる","is_common":false,"tags":["wanikani37"],"jlpt":[],"japanese":[{"word":"恥ずかしがる","reading":"はずかしがる"}],"senses":[{"english_definitions":["to be shy of","to be bashful","to be abashed","to blush"],"parts_of_speech":["Godan verb with ru ending"],"links":[],"tags":[],"restrictions":[],"see_also":[],"antonyms":[],"source":[],"info":[]}],"attribution":{"jmdict":true,"jmnedict":false,"dbpedia":false}},{"slug":"恥ずかしがり屋","is_common":false,"tags":[],"jlpt":[],"japanese":[{"word":"恥ずかしがり屋","reading":"はずかしがりや"},{"word":"恥ずかしがりや","reading":"はずかしがりや"}],"senses":[{"english_definitions":["shy person"],"parts_of_speech":["Noun"],"links":[],"tags":[],"restrictions":[],"see_also":[],"antonyms":[],"source":[],"info":[]}],"attribution":{"jmdict":true,"jmnedict":false,"dbpedia":false}},{"slug":"恥ずべき","is_common":false,"tags":[],"jlpt":[],"japanese":[{"word":"恥ずべき","reading":"はずべき"}],"senses":[{"english_definitions":["disgraceful","shameful"],"parts_of_speech":["Noun or verb acting prenominally"],"links":[],"tags":[],"restrictions":[],"see_also":[],"antonyms":[],"source":[],"info":[]}],"attribution":{"jmdict":true,"jmnedict":false,"dbpedia":false}},{"slug":"赤恥","is_common":false,"tags":[],"jlpt":[],"japanese":[{"word":"赤恥","reading":"あかはじ"},{"word":"赤っ恥","reading":"あかっぱじ"}],"senses":[{"english_definitions":["shame","disgrace"],"parts_of_speech":["Noun"],"links":[],"tags":[],"restrictions":[],"see_also":[],"antonyms":[],"source":[],"info":[]}],"attribution":{"jmdict":true,"jmnedict":false,"dbpedia":false}},{"slug":"生き恥","is_common":false,"tags":[],"jlpt":[],"japanese":[{"word":"生き恥","reading":"いきはじ"}],"senses":[{"english_definitions":["dishonor during one's life","shame experienced during one's life"],"parts_of_speech":["Noun"],"links":[],"tags":[],"restrictions":[],"see_also":["死に恥"],"antonyms":[],"source":[],"info":[]}],"attribution":{"jmdict":true,"jmnedict":false,"dbpedia":false}},{"slug":"気恥ずかしい","is_common":false,"tags":[],"jlpt":[],"japanese":[{"word":"気恥ずかしい","reading":"きはずかしい"},{"word":"気恥かしい","reading":"きはずかしい"},{"word":"気恥しい","reading":"きはずかしい"}],"senses":[{"english_definitions":["embarrassed","feeling ashamed","feeling awkward"],"parts_of_speech":["I-adjective (keiyoushi)"],"links":[],"tags":[],"restrictions":[],"see_also":[],"antonyms":[],"source":[],"info":[]}],"attribution":{"jmdict":true,"jmnedict":false,"dbpedia":false}},{"slug":"厚顔無恥","is_common":false,"tags":[],"jlpt":[],"japanese":[{"word":"厚顔無恥","reading":"こうがんむち"}],"senses":[{"english_definitions":["shameless","brazen and unscrupulous"],"parts_of_speech":["Na-adjective (keiyodoshi)","Noun"],"links":[],"tags":["Yojijukugo (four character compound)"],"restrictions":[],"see_also":[],"antonyms":[],"source":[],"info":[]}],"attribution":{"jmdict":true,"jmnedict":false,"dbpedia":false}},{"slug":"破廉恥","is_common":false,"tags":[],"jlpt":[],"japanese":[{"word":"破廉恥","reading":"はれんち"},{"reading":"ハレンチ"}],"senses":[{"english_definitions":["shameless","infamous","disgraceful"],"parts_of_speech":["Na-adjective (keiyodoshi)","Noun"],"links":[],"tags":[],"restrictions":[],"see_also":[],"antonyms":[],"source":[],"info":[]}],"attribution":{"jmdict":true,"jmnedict":false,"dbpedia":false}},{"slug":"恥さらし","is_common":true,"tags":[],"jlpt":[],"japanese":[{"word":"恥さらし","reading":"はじさらし"},{"word":"恥曝し","reading":"はじさらし"},{"word":"恥晒し","reading":"はじさらし"}],"senses":[{"english_definitions":["disgrace","shame"],"parts_of_speech":["Noun","Na-adjective (keiyodoshi)"],"links":[],"tags":[],"restrictions":[],"see_also":[],"antonyms":[],"source":[],"info":[]}],"attribution":{"jmdict":true,"jmnedict":false,"dbpedia":false}},{"slug":"無恥","is_common":true,"tags":[],"jlpt":[],"japanese":[{"word":"無恥","reading":"むち"}],"senses":[{"english_definitions":["shameless"],"parts_of_speech":["Na-adjective (keiyodoshi)","Noun"],"links":[],"tags":[],"restrictions":[],"see_also":[],"antonyms":[],"source":[],"info":[]}],"attribution":{"jmdict":true,"jmnedict":false,"dbpedia":false}},{"slug":"恥辱","is_common":false,"tags":["wanikani48"],"jlpt":[],"japanese":[{"word":"恥辱","reading":"ちじょく"}],"senses":[{"english_definitions":["disgrace","shame","insult"],"parts_of_speech":["Noun"],"links":[],"tags":[],"restrictions":[],"see_also":[],"antonyms":[],"source":[],"info":[]}],"attribution":{"jmdict":true,"jmnedict":false,"dbpedia":false}},{"slug":"羞恥","is_common":false,"tags":[],"jlpt":[],"japanese":[{"word":"羞恥","reading":"しゅうち"}],"senses":[{"english_definitions":["shyness","bashfulness","shame"],"parts_of_speech":["Noun"],"links":[],"tags":[],"restrictions":[],"see_also":[],"antonyms":[],"source":[],"info":[]}],"attribution":{"jmdict":true,"jmnedict":false,"dbpedia":false}},{"slug":"恥をかく","is_common":false,"tags":[],"jlpt":[],"japanese":[{"word":"恥をかく","reading":"はじをかく"},{"word":"恥を掻く","reading":"はじをかく"}],"senses":[{"english_definitions":["to be embarrassed","to lose face"],"parts_of_speech":["Expressions (phrases, clauses, etc.)","Godan verb with ku ending"],"links":[],"tags":[],"restrictions":[],"see_also":[],"antonyms":[],"source":[],"info":[]}],"attribution":{"jmdict":true,"jmnedict":false,"dbpedia":false}}]}