{"meta":{"status":200},"data":[{"slug":"投票","is_common":true,"tags":["wanikani25"],"jlpt":["jlpt-n3"],"japanese":[{"word":"投票","reading":"とうひょう"}],"senses":[{"english_definitions":["voting","ballot","poll","vote"],"parts_of_speech":["Noun","Suru verb","Intransitive verb"],"links":[],"tags":[],"restrictions":[],"see_also":[],"antonyms":[],"source":[],"info":[]},{"english_definitions":["Voting"],"parts_of_speech":["Wikipedia definition"],"links":[{"text":"Read “Voting” on English Wikipedia","url":"http://en.wikipedia.org/wiki/Voting?oldid=493277640"},{"text":"Read “投票” on Japanese Wikipedia","url":"http://ja.wikipedia.org/wiki/投票?oldid=42524970"}],"tags":[],"restrictions":[],"see_also":[],"antonyms":[],"source":[],"info":[],"sentences":[]}],"attribution":{"jmdict":true,"jmnedict":false,"dbpedia":"http://dbpedia.org/resource/Voting"}},{"slug":"投資","is_common":true,"tags":["wanikani21"],"jlpt":["jlpt-n1"],"japanese":[{"word":"投資","reading":"とうし"}],"senses":[{"english_definitions":["investment"],"parts_of_speech":["Noun","Suru verb","Transitive verb","Intransitive verb"],"links":[],"tags":[],"restrictions":[],"see_also":[],"antonyms":[],"source":[],"info":[]},{"english_definitions":["Investment"],"parts_of_speech":["Wikipedia definition"],"links":[{"text":"Read “Investment” on English Wikipedia","url":"http://en.wikipedia.org/wiki/Investment?oldid=493202105"},{"text":"Read “投資” on Japanese Wikipedia","url":"http://ja.wikipedia.org/wiki/投資?oldid=41036047"}],"tags":[],"restrictions":[],"see_also":[],"antonyms":[],"source":[],"info":[],"sentences":[]}],"attribution":{"jmdict":true,"jmnedict":false,"dbpedia":"http://dbpedia.org/resource/Investment"}},{"slug":"投げる","is_common":true,"tags":["wanikani8"],"jlpt":["jlpt-n4"],"japanese":[{"word":"投げる","reading":"なげる"}],"senses":[{"english_definitions":["to throw","to hurl","to fling","to toss","to cast"],"parts_of_speech":["Ichidan verb","Transitive verb"],"links":[],"tags":[],"restrictions":[],"see_also":[],"antonyms":[],"source":[],"info":[]},{"english_definitions":["to give up","to abandon","to throw away"],"parts_of_speech":["Ichidan verb","Transitive verb"],"links":[],"tags":[],"restrictions":[],"see_also":[],"antonyms":[],"source":[],"info":[]},{"english_definitions":["to cast (a glance, shadow, doubt, etc.)"],"parts_of_speech":["Ichidan verb","Transitive verb"],"links":[],"tags":[],"restrictions":[],"see_also":[],"antonyms":[],"source":[],"info":[]}],"attribution":{"jmdict":true,"jmnedict":false,"dbpedia":false}},{"slug":"投入","is_common":true,"tags":[],"jlpt":["jlpt-n1"],"japanese":[{"word":"投入","reading":"とうにゅう"}],"senses":[{"english_definitions":["throwing in","inserting","depositing (e.g. a ballot)"],"parts_of_speech":["Noun","Suru verb"],"links":[],"tags":[],"restrictions":[],"see_also":[],"antonyms":[],"source":[],"info":[]},{"english_definitions":["investment","commitment (of funds, personnel, etc.)","injection","infusion"],"parts_of_speech":["Noun","Suru verb"],"links":[],"tags":[],"restrictions":[],"see_also":[],"antonyms":[],"source":[],"info":[]},{"english_definitions":["launching (a product into the market)","introduction"],"parts_of_speech":["Noun","Suru verb"],"links":[],"tags":[],"restrictions":[],"see_also":[],"antonyms":[],"source":[],"info":[]},{"english_definitions":["submitting (a job to a computer)","issuing (a command)"],"parts_of_speech":["Noun","Suru verb"],"links":[],"tags":["Computing"],"restrictions":[],"see_also":[],"antonyms":[],"source":[],"info":[]}],"attribution":{"jmdict":true,"jmnedict":false,"dbpedia":false}},{"slug":"投げ出す","is_common":true,"tags":[],"jlpt":["jlpt-n1"],"japanese":[{"word":"投げ出す","reading":"なげだす"}],"senses":[{"english_definitions":["to throw down","to throw out","to stretch out (one's legs)"],"parts_of_speech":["Godan verb with su ending","Transitive verb"],"links":[],"tags":[],"restrictions":[],"see_also":[],"antonyms":[],"source":[],"info":[]},{"english_definitions":["to abandon","to resign"],"parts_of_speech":["Godan verb with su ending","Transitive verb"],"links":[],"tags":[],"restrictions":[],"see_also":[],"antonyms":[],"source":[],"info":[]},{"english_definitions":["to give freely","to give generously","to sacrifice (e.g. one's life)"],"parts_of_speech":["Godan verb with su ending","Transitive verb"],"links":[],"tags":[],"restrictions":[],"see_also":[],"antonyms":[],"source":[],"info":[]},{"english_definitions":["to start to throw"],"parts_of_speech":["Godan verb with su ending","Transitive verb"],"links":[],"tags":[],"restrictions":[],"see_also":[],"antonyms":[],"source":[],"info":[]}],"attribution":{"jmdict":true,"jmnedict":false,"dbpedia":false}},{"slug":"投手","is_common":true,"tags":["wanikani8"],"jlpt":[],"japanese":[{"word":"投手","reading":"とうしゅ"}],"senses":[{"english_definitions":["pitcher"],"parts_of_speech":["Noun"],"links":[],"tags":["Baseball"],"restrictions":[],"see_also":[],"antonyms":[],"source":[],"info":[]},{"english_definitions":["Pitcher"],"parts_of_speech":["Wikipedia definition"],"links":[{"text":"Read “Pitcher” on English Wikipedia","url":"http://en.wikipedia.org/wiki/Pitcher?oldid=493109073"},{"text":"Read “投手” on Japanese Wikipedia","url":"http://ja.wikipedia.org/wiki/投手?oldid=42534134"}],"tags":[],"restrictions":[],"see_also":[],"antonyms":[],"source":[],"info":[],"sentences":[]}],"attribution":{"jmdict":true,"jmnedict":false,"dbpedia":"http://dbpedia.org/resource/Pitcher"}},{"slug":"投機","is_common":true,"tags":[],"jlpt":[],"japanese":[{"word":"投機","reading":"とうき"}],"senses":[{"english_definitions":["speculation","venture","stockjobbing","gambling (on stocks)"],"parts_of_speech":["Noun"],"links":[],"tags":[],"restrictions":[],"see_also":[],"antonyms":[],"source":[],"info":[]},{"english_definitions":["Speculation"],"parts_of_speech":["Wikipedia definition"],"links":[{"text":"Read “Speculation” on English Wikipedia","url":"http://en.wikipedia.org/wiki/Speculation?oldid=492661899"},{"text":"Read “投機” on Japanese Wikipedia","url":"http://ja.wikipedia.org/wiki/投機?oldid=41509401"}],"tags":[],"restrictions":[],"see_also":[],"antonyms":[],"source":[],"info":[],"sentences":[]}],"attribution":{"jmdict":true,"jmnedict":false,"dbpedia":"http://dbpedia.org/resource/Speculation"}},{"slug":"投稿","is_common":true,"tags":["wanikani53"],"jlpt":[],"japanese":[{"word":"投稿","reading":"とうこう"}],"senses":[{"english_definitions":["contribution (to a newspaper, magazine, etc.)","submission","post (on a blog, social media, etc.)"],"parts_of_speech":["Noun","Suru verb","Transitive verb","Intransitive verb"],"links":[],"tags":[],"restrictions":[],"see_also":[],"antonyms":[],"source":[],"info":[]}],"attribution":{"jmdict":true,"jmnedict":false,"dbpedia":false}},{"slug":"投じる","is_common":true,"tags":[],"jlpt":[],"japanese":[{"word":"投じる","reading":"とうじる"}],"senses":[{"english_definitions":["to throw","to cast (e.g. vote, light, shadow)"],"parts_of_speech":["Ichidan verb","Transitive verb"],"links":[],"tags":[],"restrictions":[],"see_also":[],"antonyms":[],"source":[],"info":[]},{"english_definitions":["to devote oneself (e.g. to a cause)"],"parts_of_speech":["Ichidan verb","Transitive verb"],"links":[],"tags":[],"restrictions":[],"see_also":["身を投じる"],"antonyms":[],"source":[],"info":["in the form of 身を投じる"]},{"english_definitions":["to invest","to put in"],"parts_of_speech":["Ichidan verb","Transitive verb"],"links":[],"tags":[],"restrictions":[],"see_also":[],"antonyms":[],"source":[],"info":[]},{"english_definitions":["to administer (medicine)","to give"],"parts_of_speech":["Ichidan verb","Transitive verb"],"links":[],"tags":[],"restrictions":[],"see_also":[],"antonyms":[],"source":[],"info":[]},{"english_definitions":["to surrender"],"parts_of_speech":["Ichidan verb","Intransitive verb"],"links":[],"tags":[],"restrictions":[],"see_also":[],"antonyms":[],"source":[],"info":[]},{"english_definitions":["to take advantage of","to make full use of"],"parts_of_speech":["Ichidan verb","Intransitive verb"],"links":[],"tags":[],"restrictions":[],"see_also":[],"antonyms":[],"source":[],"info":[]},{"english_definitions":["to fit well with","to match with","to be in tune with"],"parts_of_speech":["Ichidan verb","Intransitive verb"],"links":[],"tags":[],"restrictions":[],"see_also":[],"antonyms":[],"source":[],"info":[]},{"english_definitions":["to stay (at a lodging)"],"parts_of_speech":["Ichidan verb","Intransitive verb"],"links":[],"tags":[],"restrictions":[],"see_also":[],"antonyms":[],"source":[],"info":[]}],"attribution":{"jmdict":true,"jmnedict":false,"dbpedia":false}},{"slug":"投げ込む","is_common":true,"tags":[],"jlpt":[],"japanese":[{"word":"投げ込む","reading":"なげこむ"},{"word":"投げこむ","reading":"なげこむ"}],"senses":[{"english_definitions":["to throw into"],"parts_of_speech":["Godan verb with mu ending","Transitive verb"],"links":[],"tags":[],"restrictions":[],"see_also":[],"antonyms":[],"source":[],"info":[]}],"attribution":{"jmdict":true,"jmnedict":false,"dbpedia":false}},{"slug":"国民投票","is_common":true,"tags":[],"jlpt":[],"japanese":[{"word":"国民投票","reading":"こくみんとうひょう"}],"senses":[{"english_definitions":["national referendum"],"parts_of_speech":["Noun"],"links":[],"tags":[],"restrictions":[],"see_also":[],"antonyms":[],"source":[],"info":[]}],"attribution":{"jmdict":true,"jmnedict":false,"dbpedia":false}},{"slug":"投下","is_common":true,"tags":[],"jlpt":[],"japanese":[{"word":"投下","reading":"とうか"}],"senses":[{"english_definitions":["throwing down","dropping","airdrop"],"parts_of_speech":["Noun","Suru verb"],"links":[],"tags":[],"restrictions":[],"see_also":[],"antonyms":[],"source":[],"info":[]},{"english_definitions":["investment"],"parts_of_speech":["Noun","Suru verb"],"links":[],"tags":[],"restrictions":[],"see_also":[],"antonyms":[],"source":[],"info":[]}],"attribution":{"jmdict":true,"jmnedict":false,"dbpedia":false}},{"slug":"投与","is_common":true,"tags":[],"jlpt":[],"japanese":[{"word":"投与","reading":"とうよ"}],"senses":[{"english_definitions":["administration (of medicine)"],"parts_of_speech":["Noun","Suru verb","Transitive verb"],"links":[],"tags":["Medicine"],"restrictions":[],"see_also":[],"antonyms":[],"source":[],"info":[]}],"attribution":{"jmdict":true,"jmnedict":false,"dbpedia":false}},{"slug":"投手戦","is_common":true,"tags":[],"jlpt":[],"japanese":[{"word":"投手戦","reading":"とうしゅせん"}],"senses":[{"english_definitions":["pitching duel","pitchers' battle"],"parts_of_speech":["Noun"],"links":[],"tags":[],"restrictions":[],"see_also":[],"antonyms":[],"source":[],"info":[]}],"attribution":{"jmdict":true,"jmnedict":false,"dbpedia":false}},{"slug":"投薬","is_common":true,"tags":[],"jlpt":[],"japanese":[{"word":"投薬","reading":"とうやく"}],"senses":[{"english_definitions":["administration","medication","dosage"],"parts_of_speech":["Noun","Suru verb","Transitive verb","Intransitive verb"],"links":[],"tags":[],"restrictions":[],"see_also":[],"antonyms":[],"source":[],"info":[]}],"attribution":{"jmdict":true,"jmnedict":false,"dbpedia":false}},{"slug":"投球","is_common":true,"tags":[],"jlpt":[],"japanese":[{"word":"投球","reading":"とうきゅう"}],"senses":[{"english_definitions":["pitching","throwing a ball","bowling (in cricket)","pitched ball"],"parts_of_speech":["Noun","Suru verb","Intransitive verb"],"links":[],"tags":[],"restrictions":[],"see_also":[],"antonyms":[],"source":[],"info":[]}],"attribution":{"jmdict":true,"jmnedict":false,"dbpedia":false}},{"slug":"身投げ","is_common":true,"tags":[],"jlpt":[],"japanese":[{"word":"身投げ","reading":"みなげ"}],"senses":[{"english_definitions":["throwing oneself (e.g. into the water to commit suicide)"],"parts_of_speech":["Noun","Suru verb","Intransitive verb"],"links":[],"tags":[],"restrictions":[],"see_also":[],"antonyms":[],"source":[],"info":[]}],"attribution":{"jmdict":true,"jmnedict":false,"dbpedia":false}},{"slug":"投函","is_common":true,"tags":[],"jlpt":[],"japanese":[{"word":"投函","reading":"とうかん"},{"word":"投かん","reading":"とうかん"}],"senses":[{"english_definitions":["mailing","posting"],"parts_of_speech":["Noun","Suru verb","Transitive verb"],"links":[],"tags":[],"restrictions":[],"see_also":[],"antonyms":[],"source":[],"info":[]}],"attribution":{"jmdict":true,"jmnedict":false,"dbpedia":false}},{"slug":"投付ける","is_common":false,"tags":["wanikani10"],"jlpt":[],"japanese":[{"word":"投げつける","reading":"なげつける"},{"word":"投げ付ける","reading":"なげつける"},{"word":"投付ける","reading":"なげつける"}],"senses":[{"english_definitions":["to throw at","to throw something at a person","to throw a person down"],"parts_of_speech":["Ichidan verb","Transitive verb"],"links":[],"tags":[],"restrictions":[],"see_also":[],"antonyms":[],"source":[],"info":[]}],"attribution":{"jmdict":true,"jmnedict":false,"dbpedia":false}},{"slug":"投げ掛ける","is_common":false,"tags":[],"jlpt":[],"japanese":[{"word":"投げかける","reading":"なげかける"},{"word":"投げ掛ける","reading":"なげかける"}],"senses":[{"english_definitions":["to throw at","to turn","to raise"],"parts_of_speech":["Ichidan verb","Transitive verb"],"links":[],"tags":[],"restrictions":[],"see_also":[],"antonyms":[],"source":[],"info":[]}],"attribution":{"jmdict":true,"jmnedict":false,"dbpedia":false}}]}