{"meta":{"status":200},"data":[{"slug":"掏摸","is_common":true,"tags":[],"jlpt":["jlpt-n4","jlpt-n2"],"japanese":[{"word":"掏摸","reading":"すり"},{"word":"掏児","reading":"すり"},{"reading":"スリ"}],"senses":[{"english_definitions":["pickpocket"],"parts_of_speech":["Noun"],"links":[],"tags":["Usually written using kana alone"],"restrictions":[],"see_also":[],"antonyms":[],"source":[],"info":[]}],"attribution":{"jmdict":true,"jmnedict":false,"dbpedia":false}},{"slug":"掏る","is_common":false,"tags":[],"jlpt":[],"japanese":[{"word":"掏る","reading":"する"},{"reading":"スる"}],"senses":[{"english_definitions":["to pickpocket","to steal"],"parts_of_speech":["Godan verb with ru ending","Transitive verb"],"links":[],"tags":["Usually written using kana alone"],"restrictions":[],"see_also":["すり"],"antonyms":[],"source":[],"info":[]}],"attribution":{"jmdict":true,"jmnedict":false,"dbpedia":false}},{"slug":"すり替える","is_common":false,"tags":[],"jlpt":[],"japanese":[{"word":"すり替える","reading":"すりかえる"},{"word":"摩り替える","reading":"すりかえる"},{"word":"擦り替える","reading":"すりかえる"},{"word":"掏り替える","reading":"すりかえる"},{"word":"掏替える","reading":"すりかえる"},{"word":"摺り替える","reading":"すりかえる"}],"senses":[{"english_definitions":["to switch (secretly)","to substitute","to sidestep (an issue)"],"parts_of_speech":["Ichidan verb","Transitive verb"],"links":[],"tags":[],"restrictions":[],"see_also":[],"antonyms":[],"source":[],"info":[]}],"attribution":{"jmdict":true,"jmnedict":false,"dbpedia":false}}]}