{"meta":{"status":200},"data":[{"slug":"打つ","is_common":true,"tags":["wanikani4"],"jlpt":["jlpt-n4"],"japanese":[{"word":"打つ","reading":"うつ"},{"word":"拍つ","reading":"うつ"},{"word":"搏つ","reading":"うつ"},{"word":"撲つ","reading":"うつ"},{"word":"擣つ","reading":"うつ"}],"senses":[{"english_definitions":["to hit","to strike","to knock","to beat","to punch","to slap","to tap","to bang","to clap","to pound"],"parts_of_speech":["Godan verb with tsu ending","Transitive verb"],"links":[],"tags":[],"restrictions":[],"see_also":[],"antonyms":[],"source":[],"info":[]},{"english_definitions":["to strike (noon, etc.)","to sound (cymbals, etc.)","to beat (a drum, etc.)"],"parts_of_speech":["Godan verb with tsu ending","Transitive verb"],"links":[],"tags":[],"restrictions":[],"see_also":[],"antonyms":[],"source":[],"info":[]},{"english_definitions":["to beat (rhythmically, e.g. pulse, waves, etc.)"],"parts_of_speech":["Godan verb with tsu ending","Transitive verb"],"links":[],"tags":[],"restrictions":[],"see_also":[],"antonyms":[],"source":[],"info":[]},{"english_definitions":["to move","to impress","to touch"],"parts_of_speech":["Godan verb with tsu ending","Transitive verb"],"links":[],"tags":[],"restrictions":[],"see_also":[],"antonyms":[],"source":[],"info":[]},{"english_definitions":["to drive in","to hammer in","to put in","to inject","to vaccinate"],"parts_of_speech":["Godan verb with tsu ending","Transitive verb"],"links":[],"tags":[],"restrictions":[],"see_also":[],"antonyms":[],"source":[],"info":[]},{"english_definitions":["to type","to send","to transmit"],"parts_of_speech":["Godan verb with tsu ending","Transitive verb"],"links":[],"tags":[],"restrictions":[],"see_also":[],"antonyms":[],"source":[],"info":[]},{"english_definitions":["to insert","to write in","to mark"],"parts_of_speech":["Godan verb with tsu ending","Transitive verb"],"links":[],"tags":[],"restrictions":[],"see_also":[],"antonyms":[],"source":[],"info":[]},{"english_definitions":["to make (noodles, etc.)","to prepare"],"parts_of_speech":["Godan verb with tsu ending","Transitive verb"],"links":[],"tags":[],"restrictions":[],"see_also":[],"antonyms":[],"source":[],"info":[]},{"english_definitions":["to till (soil)"],"parts_of_speech":["Godan verb with tsu ending","Transitive verb"],"links":[],"tags":[],"restrictions":[],"see_also":[],"antonyms":[],"source":[],"info":[]},{"english_definitions":["to sprinkle","to throw","to cast"],"parts_of_speech":["Godan verb with tsu ending","Transitive verb"],"links":[],"tags":[],"restrictions":[],"see_also":[],"antonyms":[],"source":[],"info":[]},{"english_definitions":["to do","to carry out","to play","to perform","to engage in (gambling, etc.)"],"parts_of_speech":["Godan verb with tsu ending","Transitive verb"],"links":[],"tags":[],"restrictions":[],"see_also":[],"antonyms":[],"source":[],"info":[]},{"english_definitions":["to pay (a deposit, etc.)"],"parts_of_speech":["Godan verb with tsu ending","Transitive verb"],"links":[],"tags":[],"restrictions":[],"see_also":[],"antonyms":[],"source":[],"info":[]},{"english_definitions":["to visit (on a pilgrimage)"],"parts_of_speech":["Godan verb with tsu ending","Transitive verb"],"links":[],"tags":[],"restrictions":[],"see_also":[],"antonyms":[],"source":[],"info":[]},{"english_definitions":["to line (a coat)"],"parts_of_speech":["Godan verb with tsu ending","Transitive verb"],"links":[],"tags":[],"restrictions":[],"see_also":[],"antonyms":[],"source":[],"info":[]},{"english_definitions":["to bind (a criminal)"],"parts_of_speech":["Godan verb with tsu ending","Transitive verb"],"links":[],"tags":[],"restrictions":[],"see_also":[],"antonyms":[],"source":[],"info":[]}],"attribution":{"jmdict":true,"jmnedict":false,"dbpedia":false}},{"slug":"脈拍","is_common":true,"tags":["wanikani56"],"jlpt":[],"japanese":[{"word":"脈拍","reading":"みゃくはく"},{"word":"脈搏","reading":"みゃくはく"}],"senses":[{"english_definitions":["pulse","pulse rate","pulsation","stroke of pulse"],"parts_of_speech":["Noun","Noun which may take the genitive case particle 'no'"],"links":[],"tags":["Medicine"],"restrictions":[],"see_also":[],"antonyms":[],"source":[],"info":[]}],"attribution":{"jmdict":true,"jmnedict":false,"dbpedia":false}},{"slug":"羽撃く","is_common":true,"tags":[],"jlpt":[],"japanese":[{"word":"羽ばたく","reading":"はばたく"},{"word":"羽撃く","reading":"はばたく"},{"word":"羽搏く","reading":"はばたく"}],"senses":[{"english_definitions":["to flap (wings)"],"parts_of_speech":["Godan verb with ku ending","Intransitive verb"],"links":[],"tags":[],"restrictions":[],"see_also":[],"antonyms":[],"source":[],"info":[]},{"english_definitions":["to spread one's wings","to go out into the world"],"parts_of_speech":["Godan verb with ku ending","Intransitive verb"],"links":[],"tags":[],"restrictions":[],"see_also":[],"antonyms":[],"source":[],"info":[]}],"attribution":{"jmdict":true,"jmnedict":false,"dbpedia":false}},{"slug":"扶桑","is_common":false,"tags":[],"jlpt":[],"japanese":[{"word":"扶桑","reading":"ふそう"},{"word":"榑桑","reading":"ふそう"},{"word":"搏桑","reading":"ふそう"}],"senses":[{"english_definitions":["divine tree or island east of China (in Chinese mythology)","Fusang"],"parts_of_speech":["Noun"],"links":[],"tags":[],"restrictions":[],"see_also":[],"antonyms":[],"source":[],"info":[]},{"english_definitions":["Japan"],"parts_of_speech":["Noun"],"links":[],"tags":[],"restrictions":[],"see_also":[],"antonyms":[],"source":[],"info":[]},{"english_definitions":["Chinese hibiscus (Hibiscus rosa-sinensis)"],"parts_of_speech":["Noun"],"links":[],"tags":[],"restrictions":[],"see_also":["ブッソウゲ"],"antonyms":[],"source":[],"info":[]},{"english_definitions":["Fusang"],"parts_of_speech":["Wikipedia definition"],"links":[{"text":"Read “Fusang” on English Wikipedia","url":"http://en.wikipedia.org/wiki/Fusang?oldid=492134399"},{"text":"Read “扶桑” on Japanese Wikipedia","url":"http://ja.wikipedia.org/wiki/扶桑?oldid=40292709"}],"tags":[],"restrictions":[],"see_also":[],"antonyms":[],"source":[],"info":[],"sentences":[]}],"attribution":{"jmdict":true,"jmnedict":false,"dbpedia":"http://dbpedia.org/resource/Fusang"}},{"slug":"拍動","is_common":false,"tags":[],"jlpt":[],"japanese":[{"word":"拍動","reading":"はくどう"},{"word":"搏動","reading":"はくどう"}],"senses":[{"english_definitions":["pulsation","pulsebeat"],"parts_of_speech":["Noun","Suru verb","Intransitive verb","Noun which may take the genitive case particle 'no'"],"links":[],"tags":[],"restrictions":[],"see_also":[],"antonyms":[],"source":[],"info":[]},{"english_definitions":["Pulse"],"parts_of_speech":["Wikipedia definition"],"links":[{"text":"Read “Pulse” on English Wikipedia","url":"http://en.wikipedia.org/wiki/Pulse?oldid=484711704"},{"text":"Read “拍動” on Japanese Wikipedia","url":"http://ja.wikipedia.org/wiki/拍動?oldid=41352891"}],"tags":[],"restrictions":[],"see_also":[],"antonyms":[],"source":[],"info":[],"sentences":[]}],"attribution":{"jmdict":true,"jmnedict":false,"dbpedia":"http://dbpedia.org/resource/Pulse"}},{"slug":"脈搏数","is_common":false,"tags":[],"jlpt":[],"japanese":[{"word":"脈搏数","reading":"みゃくはくすう"}],"senses":[{"english_definitions":["pulse rate"],"parts_of_speech":["Noun"],"links":[],"tags":[],"restrictions":[],"see_also":[],"antonyms":[],"source":[],"info":[]}],"attribution":{"jmdict":true,"jmnedict":false,"dbpedia":false}},{"slug":"竜攘虎搏","is_common":false,"tags":[],"jlpt":[],"japanese":[{"word":"竜攘虎搏","reading":"りゅうじょうこはく"}],"senses":[{"english_definitions":["fierce fighting"],"parts_of_speech":["Noun"],"links":[],"tags":[],"restrictions":[],"see_also":[],"antonyms":[],"source":[],"info":[]}],"attribution":{"jmdict":true,"jmnedict":false,"dbpedia":false}},{"slug":"破風","is_common":false,"tags":[],"jlpt":[],"japanese":[{"word":"破風","reading":"はふ"},{"word":"搏風","reading":"はふ"}],"senses":[{"english_definitions":["gable"],"parts_of_speech":["Noun","Noun which may take the genitive case particle 'no'"],"links":[],"tags":[],"restrictions":[],"see_also":[],"antonyms":[],"source":[],"info":[]}],"attribution":{"jmdict":true,"jmnedict":false,"dbpedia":false}},{"slug":"羽搏き","is_common":false,"tags":[],"jlpt":[],"japanese":[{"word":"羽搏き","reading":"はばたき"},{"word":"羽撃き","reading":"はばたき"}],"senses":[{"english_definitions":["fluttering or flapping of wings"],"parts_of_speech":["Noun","Suru verb"],"links":[],"tags":[],"restrictions":[],"see_also":[],"antonyms":[],"source":[],"info":[]}],"attribution":{"jmdict":true,"jmnedict":false,"dbpedia":false}},{"slug":"竜虎相搏つ","is_common":false,"tags":[],"jlpt":[],"japanese":[{"word":"竜虎相搏つ","reading":"りゅうこあいうつ"}],"senses":[{"english_definitions":["a fight between equally great opponents"],"parts_of_speech":["Expressions (phrases, clauses, etc.)"],"links":[],"tags":["Idiomatic expression"],"restrictions":[],"see_also":[],"antonyms":[],"source":[],"info":[]}],"attribution":{"jmdict":true,"jmnedict":false,"dbpedia":false}}]}