{"meta":{"status":200},"data":[{"slug":"瘴気","is_common":false,"tags":[],"jlpt":[],"japanese":[{"word":"瘴気","reading":"しょうき"}],"senses":[{"english_definitions":["miasma","noxious form of \"bad air\" formerly believed to cause diseases"],"parts_of_speech":["Noun"],"links":[],"tags":[],"restrictions":[],"see_also":[],"antonyms":[],"source":[],"info":[]},{"english_definitions":["Miasma theory"],"parts_of_speech":["Wikipedia definition"],"links":[{"text":"Read “Miasma theory” on English Wikipedia","url":"http://en.wikipedia.org/wiki/Miasma_theory?oldid=485663968"},{"text":"Read “瘴気” on Japanese Wikipedia","url":"http://ja.wikipedia.org/wiki/瘴気?oldid=42509261"}],"tags":[],"restrictions":[],"see_also":[],"antonyms":[],"source":[],"info":[],"sentences":[]}],"attribution":{"jmdict":true,"jmnedict":false,"dbpedia":"http://dbpedia.org/resource/Miasma_theory"}},{"slug":"瘴癘","is_common":false,"tags":[],"jlpt":[],"japanese":[{"word":"瘴癘","reading":"しょうれい"}],"senses":[{"english_definitions":["tropical disease (e.g. malaria)"],"parts_of_speech":["Noun"],"links":[],"tags":[],"restrictions":[],"see_also":[],"antonyms":[],"source":[],"info":[]}],"attribution":{"jmdict":true,"jmnedict":false,"dbpedia":false}}]}