{"meta":{"status":200},"data":[{"slug":"騙す","is_common":true,"tags":[],"jlpt":["jlpt-n2","jlpt-n1"],"japanese":[{"word":"騙す","reading":"だます"},{"word":"瞞す","reading":"だます"}],"senses":[{"english_definitions":["to trick","to cheat","to deceive"],"parts_of_speech":["Godan verb with su ending","Transitive verb"],"links":[],"tags":[],"restrictions":[],"see_also":[],"antonyms":[],"source":[],"info":[]},{"english_definitions":["to coax","to wheedle","to soothe and humor (humour)"],"parts_of_speech":["Godan verb with su ending","Transitive verb"],"links":[],"tags":[],"restrictions":[],"see_also":["宥め賺す"],"antonyms":[],"source":[],"info":[]}],"attribution":{"jmdict":true,"jmnedict":false,"dbpedia":false}},{"slug":"欺瞞","is_common":false,"tags":[],"jlpt":[],"japanese":[{"word":"欺瞞","reading":"ぎまん"},{"word":"欺まん","reading":"ぎまん"}],"senses":[{"english_definitions":["deception","deceit"],"parts_of_speech":["Noun","Suru verb","Transitive verb"],"links":[],"tags":[],"restrictions":[],"see_also":[],"antonyms":[],"source":[],"info":[]}],"attribution":{"jmdict":true,"jmnedict":false,"dbpedia":false}},{"slug":"欺瞞者","is_common":false,"tags":[],"jlpt":[],"japanese":[{"word":"欺瞞者","reading":"ぎまんしゃ"}],"senses":[{"english_definitions":["deceiver","a fraud"],"parts_of_speech":["Noun"],"links":[],"tags":[],"restrictions":[],"see_also":[],"antonyms":[],"source":[],"info":[]}],"attribution":{"jmdict":true,"jmnedict":false,"dbpedia":false}},{"slug":"蟹瞞","is_common":false,"tags":[],"jlpt":[],"japanese":[{"word":"蟹瞞","reading":"かにだまし"},{"word":"蟹瞞し","reading":"かにだまし"},{"reading":"カニダマシ"}],"senses":[{"english_definitions":["porcelain crab (any decapod crustacean of family Porcellanidae)"],"parts_of_speech":["Noun"],"links":[],"tags":["Usually written using kana alone"],"restrictions":[],"see_also":[],"antonyms":[],"source":[],"info":[]}],"attribution":{"jmdict":true,"jmnedict":false,"dbpedia":false}},{"slug":"欺瞞的","is_common":false,"tags":[],"jlpt":[],"japanese":[{"word":"欺瞞的","reading":"ぎまんてき"}],"senses":[{"english_definitions":["deceptive","fraudulent"],"parts_of_speech":["Na-adjective (keiyodoshi)"],"links":[],"tags":[],"restrictions":[],"see_also":[],"antonyms":[],"source":[],"info":[]}],"attribution":{"jmdict":true,"jmnedict":false,"dbpedia":false}},{"slug":"瞞着","is_common":false,"tags":[],"jlpt":[],"japanese":[{"word":"瞞着","reading":"まんちゃく"}],"senses":[{"english_definitions":["deception","cheating","trickery","fraud"],"parts_of_speech":["Noun","Suru verb","Transitive verb"],"links":[],"tags":[],"restrictions":[],"see_also":[],"antonyms":[],"source":[],"info":[]}],"attribution":{"jmdict":true,"jmnedict":false,"dbpedia":false}},{"slug":"自己欺瞞","is_common":false,"tags":[],"jlpt":[],"japanese":[{"word":"自己欺瞞","reading":"じこぎまん"},{"word":"自己欺まん","reading":"じこぎまん"}],"senses":[{"english_definitions":["self-deception","self-deceit"],"parts_of_speech":["Noun","Noun which may take the genitive case particle 'no'"],"links":[],"tags":["Yojijukugo (four character compound)"],"restrictions":[],"see_also":[],"antonyms":[],"source":[],"info":[]}],"attribution":{"jmdict":true,"jmnedict":false,"dbpedia":false}},{"slug":"瞞着手段","is_common":false,"tags":[],"jlpt":[],"japanese":[{"word":"瞞着手段","reading":"まんちゃくしゅだん"}],"senses":[{"english_definitions":["ruse","trick","deception tactics"],"parts_of_speech":["Noun"],"links":[],"tags":["Yojijukugo (four character compound)"],"restrictions":[],"see_also":[],"antonyms":[],"source":[],"info":[]}],"attribution":{"jmdict":true,"jmnedict":false,"dbpedia":false}}]}