{"meta":{"status":200},"data":[{"slug":"蕾","is_common":true,"tags":[],"jlpt":["jlpt-n1"],"japanese":[{"word":"蕾","reading":"つぼみ"},{"word":"莟","reading":"つぼみ"}],"senses":[{"english_definitions":["(flower) bud"],"parts_of_speech":["Noun"],"links":[],"tags":[],"restrictions":[],"see_also":[],"antonyms":[],"source":[],"info":[]},{"english_definitions":["promising young person","budding beauty"],"parts_of_speech":["Noun"],"links":[],"tags":[],"restrictions":[],"see_also":[],"antonyms":[],"source":[],"info":[]},{"english_definitions":["Bud"],"parts_of_speech":["Wikipedia definition"],"links":[{"text":"Read “Bud” on English Wikipedia","url":"http://en.wikipedia.org/wiki/Bud?oldid=494826545"},{"text":"Read “蕾” on Japanese Wikipedia","url":"http://ja.wikipedia.org/wiki/蕾?oldid=42617612"}],"tags":[],"restrictions":[],"see_also":[],"antonyms":[],"source":[],"info":[],"sentences":[]}],"attribution":{"jmdict":true,"jmnedict":false,"dbpedia":"http://dbpedia.org/resource/Bud"}},{"slug":"蕾む","is_common":false,"tags":[],"jlpt":[],"japanese":[{"word":"蕾む","reading":"つぼむ"},{"word":"莟む","reading":"つぼむ"}],"senses":[{"english_definitions":["to bud","to be budding"],"parts_of_speech":["Godan verb with mu ending","Intransitive verb"],"links":[],"tags":["Archaism"],"restrictions":[],"see_also":[],"antonyms":[],"source":[],"info":[]}],"attribution":{"jmdict":true,"jmnedict":false,"dbpedia":false}}]}