{"meta":{"status":200},"data":[{"slug":"隣","is_common":true,"tags":["wanikani40"],"jlpt":["jlpt-n5"],"japanese":[{"word":"隣","reading":"となり"},{"word":"隣り","reading":"となり"},{"word":"鄰","reading":"となり"}],"senses":[{"english_definitions":["next (to)","adjoining","adjacent"],"parts_of_speech":["Noun which may take the genitive case particle 'no'","Noun"],"links":[],"tags":[],"restrictions":[],"see_also":[],"antonyms":[],"source":[],"info":[]},{"english_definitions":["house next door","neighbouring house","next-door neighbour","next-door neighbor"],"parts_of_speech":["Noun","Noun which may take the genitive case particle 'no'"],"links":[],"tags":[],"restrictions":[],"see_also":[],"antonyms":[],"source":[],"info":[]}],"attribution":{"jmdict":true,"jmnedict":false,"dbpedia":false}}]}